twilix/__init__.py
twilix_python-0.0.7.dist-info/LICENSE
twilix_python-0.0.7.dist-info/METADATA
twilix_python-0.0.7.dist-info/WHEEL
twilix_python-0.0.7.dist-info/top_level.txt
twilix_python-0.0.7.dist-info/RECORD
